{
    "exam_code": "IIT-JAM",
    "exam_name": "IIT Joint Admission Test for M.Sc. 2026",
    "full_form": "Indian Institute of Technology - Joint Admission Test for Masters",
    "exam_level": "NATIONAL",
    "exam_sector": "POST GRADUATION ADMISSION",
    "exam_target": "PG ADMISSION",
    "exam_frequency_year": "1",
    "conducting_body": "IIT (Indian Institute of Technology)",
    "posts_classes_courses_departments_academies": "BIOTECHNOLOGY, CHEMISTRY, ECONOMICS, GEOLOGY, MATHEMATICAL STATISTICS, MATHEMATICS, PHYSICS",

    "academies": {
        "BIOTECHNOLOGY": {
            "exam_tiers": "SINGLE",
            "gender": "MALE, FEMALE, TRANSGENDER",
            "special_gender_eligibility": "",
            "marital_status": "NOT APPLICABLE",
            "pwd_status": "ELIGIBLE",
            "domicile": "PAN INDIA",
            "nationality": "Indian nationals, OCI/PIO",
            "caste_category": "GEN, OBC-NCL, EWS, SC, ST",

            "age_criteria_type": "NO_AGE_LIMIT",
            "minimum_age": "",
            "maximum_age": "",
            "between_age": {},
            "age_relaxation": "",

            "maximum_attempts_allowed": "NO LIMIT",

            "highest_education_qualification": "BACHELOR DEGREE",
            "eligibility_marks": "55% GEN/OBC, 50% SC/ST/PWD",
            "eligibility_education_course": "B.SC. / B.TECH / B.E.",
            "eligibility_education_course_subject": "BIOTECHNOLOGY / BIOLOGICAL SCIENCES / BIOCHEMISTRY / BIOINFORMATICS / BOTANY / MICROBIOLOGY / ZOOLOGY / BIOMEDICAL SCIENCES",
            "eligibility_course_year": "PASSED, APPEARING FINAL YEAR",
            "percentage_10th_requirement": "",
            "percentage_12th_requirement": "",
            "subjects_at_10th": "",
            "subjects_at_12th": "BIOLOGY / CHEMISTRY / MATHEMATICS",
            "active_backlogs_allowed": "NO",
            "gap_years_allowed": "NO LIMIT",

            "exam_subjects": "BIOTECHNOLOGY",
            "exam_pattern": "MCQ + MSQ + NAT",
            "exam_sections": "SECTION A (MCQ), SECTION B (MSQ), SECTION C (NAT)",
            "mode_of_exam": "ONLINE (CBT)",
            "exam_duration": "3 HOURS",
            "total_marks": "100",
            "number_of_questions": "60",
            "marking_scheme": "NEGATIVE MARKING 1/3 FOR MCQ, NO NEGATIVE FOR MSQ AND NAT",
            "paper_medium": "ENGLISH",
            "exam_date": "FEBRUARY 2026",

            "educational_stream_restriction": "SCIENCE STREAM",

            "ncc_wing": "",
            "ncc_certificate": "",
            "ncc_certificate_grade": "",

            "sports_quota_eligibility": "",
            "cpl_holder": "",

            "height_cm": "",
            "weight_kg": "",
            "vision_eyesight": "",

            "language_proficiency": "ENGLISH",
            "driving_license_type": "",

            "current_employment_status": "",
            "work_experience_required": "NO",
            "work_experience_years": "",
            "ex_servicemen_status": ""
        },
        "CHEMISTRY": {
            "exam_tiers": "SINGLE",
            "gender": "MALE, FEMALE, TRANSGENDER",
            "special_gender_eligibility": "",
            "marital_status": "NOT APPLICABLE",
            "pwd_status": "ELIGIBLE",
            "domicile": "PAN INDIA",
            "nationality": "Indian nationals, OCI/PIO",
            "caste_category": "GEN, OBC-NCL, EWS, SC, ST",

            "age_criteria_type": "NO_AGE_LIMIT",
            "minimum_age": "",
            "maximum_age": "",
            "between_age": {},
            "age_relaxation": "",

            "maximum_attempts_allowed": "NO LIMIT",

            "highest_education_qualification": "BACHELOR DEGREE",
            "eligibility_marks": "55% GEN/OBC, 50% SC/ST/PWD",
            "eligibility_education_course": "B.SC.",
            "eligibility_education_course_subject": "CHEMISTRY",
            "eligibility_course_year": "PASSED, APPEARING FINAL YEAR",
            "percentage_10th_requirement": "",
            "percentage_12th_requirement": "",
            "subjects_at_10th": "",
            "subjects_at_12th": "CHEMISTRY",
            "active_backlogs_allowed": "NO",
            "gap_years_allowed": "NO LIMIT",

            "exam_subjects": "CHEMISTRY",
            "exam_pattern": "MCQ + MSQ + NAT",
            "exam_sections": "SECTION A (MCQ), SECTION B (MSQ), SECTION C (NAT)",
            "mode_of_exam": "ONLINE (CBT)",
            "exam_duration": "3 HOURS",
            "total_marks": "100",
            "number_of_questions": "60",
            "marking_scheme": "NEGATIVE MARKING 1/3 FOR MCQ, NO NEGATIVE FOR MSQ AND NAT",
            "paper_medium": "ENGLISH",
            "exam_date": "FEBRUARY 2026",

            "educational_stream_restriction": "SCIENCE STREAM",

            "ncc_wing": "",
            "ncc_certificate": "",
            "ncc_certificate_grade": "",

            "sports_quota_eligibility": "",
            "cpl_holder": "",

            "height_cm": "",
            "weight_kg": "",
            "vision_eyesight": "",

            "language_proficiency": "ENGLISH",
            "driving_license_type": "",

            "current_employment_status": "",
            "work_experience_required": "NO",
            "work_experience_years": "",
            "ex_servicemen_status": ""
        },
        "ECONOMICS": {
            "exam_tiers": "SINGLE",
            "gender": "MALE, FEMALE, TRANSGENDER",
            "special_gender_eligibility": "",
            "marital_status": "NOT APPLICABLE",
            "pwd_status": "ELIGIBLE",
            "domicile": "PAN INDIA",
            "nationality": "Indian nationals, OCI/PIO",
            "caste_category": "GEN, OBC-NCL, EWS, SC, ST",

            "age_criteria_type": "NO_AGE_LIMIT",
            "minimum_age": "",
            "maximum_age": "",
            "between_age": {},
            "age_relaxation": "",

            "maximum_attempts_allowed": "NO LIMIT",

            "highest_education_qualification": "BACHELOR DEGREE",
            "eligibility_marks": "55% GEN/OBC, 50% SC/ST/PWD",
            "eligibility_education_course": "B.A. / B.SC. / B.COM",
            "eligibility_education_course_subject": "ECONOMICS / STATISTICS / MATHEMATICS",
            "eligibility_course_year": "PASSED, APPEARING FINAL YEAR",
            "percentage_10th_requirement": "",
            "percentage_12th_requirement": "",
            "subjects_at_10th": "",
            "subjects_at_12th": "MATHEMATICS",
            "active_backlogs_allowed": "NO",
            "gap_years_allowed": "NO LIMIT",

            "exam_subjects": "ECONOMICS",
            "exam_pattern": "MCQ + MSQ + NAT",
            "exam_sections": "SECTION A (MCQ), SECTION B (MSQ), SECTION C (NAT)",
            "mode_of_exam": "ONLINE (CBT)",
            "exam_duration": "3 HOURS",
            "total_marks": "100",
            "number_of_questions": "60",
            "marking_scheme": "NEGATIVE MARKING 1/3 FOR MCQ, NO NEGATIVE FOR MSQ AND NAT",
            "paper_medium": "ENGLISH",
            "exam_date": "FEBRUARY 2026",

            "educational_stream_restriction": "",

            "ncc_wing": "",
            "ncc_certificate": "",
            "ncc_certificate_grade": "",

            "sports_quota_eligibility": "",
            "cpl_holder": "",

            "height_cm": "",
            "weight_kg": "",
            "vision_eyesight": "",

            "language_proficiency": "ENGLISH",
            "driving_license_type": "",

            "current_employment_status": "",
            "work_experience_required": "NO",
            "work_experience_years": "",
            "ex_servicemen_status": ""
        },
        "GEOLOGY": {
            "exam_tiers": "SINGLE",
            "gender": "MALE, FEMALE, TRANSGENDER",
            "special_gender_eligibility": "",
            "marital_status": "NOT APPLICABLE",
            "pwd_status": "ELIGIBLE",
            "domicile": "PAN INDIA",
            "nationality": "Indian nationals, OCI/PIO",
            "caste_category": "GEN, OBC-NCL, EWS, SC, ST",

            "age_criteria_type": "NO_AGE_LIMIT",
            "minimum_age": "",
            "maximum_age": "",
            "between_age": {},
            "age_relaxation": "",

            "maximum_attempts_allowed": "NO LIMIT",

            "highest_education_qualification": "BACHELOR DEGREE",
            "eligibility_marks": "55% GEN/OBC, 50% SC/ST/PWD",
            "eligibility_education_course": "B.SC.",
            "eligibility_education_course_subject": "GEOLOGY / APPLIED GEOLOGY / EARTH SCIENCES",
            "eligibility_course_year": "PASSED, APPEARING FINAL YEAR",
            "percentage_10th_requirement": "",
            "percentage_12th_requirement": "",
            "subjects_at_10th": "",
            "subjects_at_12th": "SCIENCE",
            "active_backlogs_allowed": "NO",
            "gap_years_allowed": "NO LIMIT",

            "exam_subjects": "GEOLOGY",
            "exam_pattern": "MCQ + MSQ + NAT",
            "exam_sections": "SECTION A (MCQ), SECTION B (MSQ), SECTION C (NAT)",
            "mode_of_exam": "ONLINE (CBT)",
            "exam_duration": "3 HOURS",
            "total_marks": "100",
            "number_of_questions": "60",
            "marking_scheme": "NEGATIVE MARKING 1/3 FOR MCQ, NO NEGATIVE FOR MSQ AND NAT",
            "paper_medium": "ENGLISH",
            "exam_date": "FEBRUARY 2026",

            "educational_stream_restriction": "SCIENCE STREAM",

            "ncc_wing": "",
            "ncc_certificate": "",
            "ncc_certificate_grade": "",

            "sports_quota_eligibility": "",
            "cpl_holder": "",

            "height_cm": "",
            "weight_kg": "",
            "vision_eyesight": "",

            "language_proficiency": "ENGLISH",
            "driving_license_type": "",

            "current_employment_status": "",
            "work_experience_required": "NO",
            "work_experience_years": "",
            "ex_servicemen_status": ""
        },
        "MATHEMATICAL_STATISTICS": {
            "exam_tiers": "SINGLE",
            "gender": "MALE, FEMALE, TRANSGENDER",
            "special_gender_eligibility": "",
            "marital_status": "NOT APPLICABLE",
            "pwd_status": "ELIGIBLE",
            "domicile": "PAN INDIA",
            "nationality": "Indian nationals, OCI/PIO",
            "caste_category": "GEN, OBC-NCL, EWS, SC, ST",

            "age_criteria_type": "NO_AGE_LIMIT",
            "minimum_age": "",
            "maximum_age": "",
            "between_age": {},
            "age_relaxation": "",

            "maximum_attempts_allowed": "NO LIMIT",

            "highest_education_qualification": "BACHELOR DEGREE",
            "eligibility_marks": "55% GEN/OBC, 50% SC/ST/PWD",
            "eligibility_education_course": "B.SC. / B.A.",
            "eligibility_education_course_subject": "STATISTICS / MATHEMATICS",
            "eligibility_course_year": "PASSED, APPEARING FINAL YEAR",
            "percentage_10th_requirement": "",
            "percentage_12th_requirement": "",
            "subjects_at_10th": "",
            "subjects_at_12th": "MATHEMATICS",
            "active_backlogs_allowed": "NO",
            "gap_years_allowed": "NO LIMIT",

            "exam_subjects": "MATHEMATICAL STATISTICS",
            "exam_pattern": "MCQ + MSQ + NAT",
            "exam_sections": "SECTION A (MCQ), SECTION B (MSQ), SECTION C (NAT)",
            "mode_of_exam": "ONLINE (CBT)",
            "exam_duration": "3 HOURS",
            "total_marks": "100",
            "number_of_questions": "60",
            "marking_scheme": "NEGATIVE MARKING 1/3 FOR MCQ, NO NEGATIVE FOR MSQ AND NAT",
            "paper_medium": "ENGLISH",
            "exam_date": "FEBRUARY 2026",

            "educational_stream_restriction": "SCIENCE STREAM",

            "ncc_wing": "",
            "ncc_certificate": "",
            "ncc_certificate_grade": "",

            "sports_quota_eligibility": "",
            "cpl_holder": "",

            "height_cm": "",
            "weight_kg": "",
            "vision_eyesight": "",

            "language_proficiency": "ENGLISH",
            "driving_license_type": "",

            "current_employment_status": "",
            "work_experience_required": "NO",
            "work_experience_years": "",
            "ex_servicemen_status": ""
        },
        "MATHEMATICS": {
            "exam_tiers": "SINGLE",
            "gender": "MALE, FEMALE, TRANSGENDER",
            "special_gender_eligibility": "",
            "marital_status": "NOT APPLICABLE",
            "pwd_status": "ELIGIBLE",
            "domicile": "PAN INDIA",
            "nationality": "Indian nationals, OCI/PIO",
            "caste_category": "GEN, OBC-NCL, EWS, SC, ST",

            "age_criteria_type": "NO_AGE_LIMIT",
            "minimum_age": "",
            "maximum_age": "",
            "between_age": {},
            "age_relaxation": "",

            "maximum_attempts_allowed": "NO LIMIT",

            "highest_education_qualification": "BACHELOR DEGREE",
            "eligibility_marks": "55% GEN/OBC, 50% SC/ST/PWD",
            "eligibility_education_course": "B.SC. / B.A.",
            "eligibility_education_course_subject": "MATHEMATICS",
            "eligibility_course_year": "PASSED, APPEARING FINAL YEAR",
            "percentage_10th_requirement": "",
            "percentage_12th_requirement": "",
            "subjects_at_10th": "",
            "subjects_at_12th": "MATHEMATICS",
            "active_backlogs_allowed": "NO",
            "gap_years_allowed": "NO LIMIT",

            "exam_subjects": "MATHEMATICS",
            "exam_pattern": "MCQ + MSQ + NAT",
            "exam_sections": "SECTION A (MCQ), SECTION B (MSQ), SECTION C (NAT)",
            "mode_of_exam": "ONLINE (CBT)",
            "exam_duration": "3 HOURS",
            "total_marks": "100",
            "number_of_questions": "60",
            "marking_scheme": "NEGATIVE MARKING 1/3 FOR MCQ, NO NEGATIVE FOR MSQ AND NAT",
            "paper_medium": "ENGLISH",
            "exam_date": "FEBRUARY 2026",

            "educational_stream_restriction": "SCIENCE STREAM",

            "ncc_wing": "",
            "ncc_certificate": "",
            "ncc_certificate_grade": "",

            "sports_quota_eligibility": "",
            "cpl_holder": "",

            "height_cm": "",
            "weight_kg": "",
            "vision_eyesight": "",

            "language_proficiency": "ENGLISH",
            "driving_license_type": "",

            "current_employment_status": "",
            "work_experience_required": "NO",
            "work_experience_years": "",
            "ex_servicemen_status": ""
        },
        "PHYSICS": {
            "exam_tiers": "SINGLE",
            "gender": "MALE, FEMALE, TRANSGENDER",
            "special_gender_eligibility": "",
            "marital_status": "NOT APPLICABLE",
            "pwd_status": "ELIGIBLE",
            "domicile": "PAN INDIA",
            "nationality": "Indian nationals, OCI/PIO",
            "caste_category": "GEN, OBC-NCL, EWS, SC, ST",

            "age_criteria_type": "NO_AGE_LIMIT",
            "minimum_age": "",
            "maximum_age": "",
            "between_age": {},
            "age_relaxation": "",

            "maximum_attempts_allowed": "NO LIMIT",

            "highest_education_qualification": "BACHELOR DEGREE",
            "eligibility_marks": "55% GEN/OBC, 50% SC/ST/PWD",
            "eligibility_education_course": "B.SC.",
            "eligibility_education_course_subject": "PHYSICS",
            "eligibility_course_year": "PASSED, APPEARING FINAL YEAR",
            "percentage_10th_requirement": "",
            "percentage_12th_requirement": "",
            "subjects_at_10th": "",
            "subjects_at_12th": "PHYSICS, MATHEMATICS",
            "active_backlogs_allowed": "NO",
            "gap_years_allowed": "NO LIMIT",

            "exam_subjects": "PHYSICS",
            "exam_pattern": "MCQ + MSQ + NAT",
            "exam_sections": "SECTION A (MCQ), SECTION B (MSQ), SECTION C (NAT)",
            "mode_of_exam": "ONLINE (CBT)",
            "exam_duration": "3 HOURS",
            "total_marks": "100",
            "number_of_questions": "60",
            "marking_scheme": "NEGATIVE MARKING 1/3 FOR MCQ, NO NEGATIVE FOR MSQ AND NAT",
            "paper_medium": "ENGLISH",
            "exam_date": "FEBRUARY 2026",

            "educational_stream_restriction": "SCIENCE STREAM",

            "ncc_wing": "",
            "ncc_certificate": "",
            "ncc_certificate_grade": "",

            "sports_quota_eligibility": "",
            "cpl_holder": "",

            "height_cm": "",
            "weight_kg": "",
            "vision_eyesight": "",

            "language_proficiency": "ENGLISH",
            "driving_license_type": "",

            "current_employment_status": "",
            "work_experience_required": "NO",
            "work_experience_years": "",
            "ex_servicemen_status": ""
        }
    }
}
